{
  "date": "2025-05-21",
  "projects": {
    "FixMe24": {
      "totalLinesAdded": 3353,
      "totalLinesRemoved": 18,
      "totalActiveTime": 64,
      "files": {
        "c:\\Users\\pk-20\\Projekte\\FixMe24\\temp_project\\src\\components\\layout\\Header.tsx": [
          {
            "timestamp": "2025-05-21T03:54:58.783Z",
            "fileName": "c:\\Users\\pk-20\\Projekte\\FixMe24\\temp_project\\src\\components\\layout\\Header.tsx",
            "fileType": ".tsx",
            "linesAdded": 1,
            "linesRemoved": 0,
            "projectName": "FixMe24",
            "content": {
              "added": [],
              "removed": []
            },
            "duration": 0,
            "language": "tsx"
          },
          {
            "timestamp": "2025-05-21T03:55:02.050Z",
            "fileName": "c:\\Users\\pk-20\\Projekte\\FixMe24\\temp_project\\src\\components\\layout\\Header.tsx",
            "fileType": ".tsx",
            "linesAdded": 211,
            "linesRemoved": 0,
            "projectName": "FixMe24",
            "content": {
              "added": [],
              "removed": []
            },
            "duration": 1,
            "language": "tsx"
          },
          {
            "timestamp": "2025-05-21T03:55:04.531Z",
            "fileName": "c:\\Users\\pk-20\\Projekte\\FixMe24\\temp_project\\src\\components\\layout\\Header.tsx",
            "fileType": ".tsx",
            "linesAdded": 0,
            "linesRemoved": 1,
            "projectName": "FixMe24",
            "content": {
              "added": [],
              "removed": []
            },
            "duration": 1,
            "language": "tsx"
          }
        ],
        "c:\\Users\\pk-20\\Projekte\\FixMe24\\temp_project\\src\\components\\layout\\Footer.tsx": [
          {
            "timestamp": "2025-05-21T03:55:39.589Z",
            "fileName": "c:\\Users\\pk-20\\Projekte\\FixMe24\\temp_project\\src\\components\\layout\\Footer.tsx",
            "fileType": ".tsx",
            "linesAdded": 1,
            "linesRemoved": 0,
            "projectName": "FixMe24",
            "content": {
              "added": [],
              "removed": []
            },
            "duration": 1,
            "language": "tsx"
          },
          {
            "timestamp": "2025-05-21T03:55:41.505Z",
            "fileName": "c:\\Users\\pk-20\\Projekte\\FixMe24\\temp_project\\src\\components\\layout\\Footer.tsx",
            "fileType": ".tsx",
            "linesAdded": 107,
            "linesRemoved": 0,
            "projectName": "FixMe24",
            "content": {
              "added": [],
              "removed": []
            },
            "duration": 1,
            "language": "tsx"
          },
          {
            "timestamp": "2025-05-21T03:55:42.390Z",
            "fileName": "c:\\Users\\pk-20\\Projekte\\FixMe24\\temp_project\\src\\components\\layout\\Footer.tsx",
            "fileType": ".tsx",
            "linesAdded": 0,
            "linesRemoved": 1,
            "projectName": "FixMe24",
            "content": {
              "added": [],
              "removed": []
            },
            "duration": 1,
            "language": "tsx"
          }
        ],
        "c:\\Users\\pk-20\\Projekte\\FixMe24\\temp_project\\src\\components\\layout\\MainLayout.tsx": [
          {
            "timestamp": "2025-05-21T03:55:57.812Z",
            "fileName": "c:\\Users\\pk-20\\Projekte\\FixMe24\\temp_project\\src\\components\\layout\\MainLayout.tsx",
            "fileType": ".tsx",
            "linesAdded": 29,
            "linesRemoved": 0,
            "projectName": "FixMe24",
            "content": {
              "added": [],
              "removed": []
            },
            "duration": 1,
            "language": "tsx"
          },
          {
            "timestamp": "2025-05-21T03:55:57.783Z",
            "fileName": "c:\\Users\\pk-20\\Projekte\\FixMe24\\temp_project\\src\\components\\layout\\MainLayout.tsx",
            "fileType": ".tsx",
            "linesAdded": 0,
            "linesRemoved": 1,
            "projectName": "FixMe24",
            "content": {
              "added": [],
              "removed": []
            },
            "duration": 1,
            "language": "tsx"
          }
        ],
        "c:\\Users\\pk-20\\Projekte\\FixMe24\\temp_project\\src\\components\\common\\LanguageSwitcher.tsx": [
          {
            "timestamp": "2025-05-21T03:56:18.014Z",
            "fileName": "c:\\Users\\pk-20\\Projekte\\FixMe24\\temp_project\\src\\components\\common\\LanguageSwitcher.tsx",
            "fileType": ".tsx",
            "linesAdded": 65,
            "linesRemoved": 0,
            "projectName": "FixMe24",
            "content": {
              "added": [],
              "removed": []
            },
            "duration": 1,
            "language": "tsx"
          },
          {
            "timestamp": "2025-05-21T03:56:18.545Z",
            "fileName": "c:\\Users\\pk-20\\Projekte\\FixMe24\\temp_project\\src\\components\\common\\LanguageSwitcher.tsx",
            "fileType": ".tsx",
            "linesAdded": 0,
            "linesRemoved": 1,
            "projectName": "FixMe24",
            "content": {
              "added": [],
              "removed": []
            },
            "duration": 1,
            "language": "tsx"
          }
        ],
        "c:\\Users\\pk-20\\Projekte\\FixMe24\\temp_project\\src\\hooks\\useAuth.ts": [
          {
            "timestamp": "2025-05-21T03:56:48.126Z",
            "fileName": "c:\\Users\\pk-20\\Projekte\\FixMe24\\temp_project\\src\\hooks\\useAuth.ts",
            "fileType": ".ts",
            "linesAdded": 1,
            "linesRemoved": 0,
            "projectName": "FixMe24",
            "content": {
              "added": [],
              "removed": []
            },
            "duration": 1,
            "language": "ts"
          },
          {
            "timestamp": "2025-05-21T03:56:48.932Z",
            "fileName": "c:\\Users\\pk-20\\Projekte\\FixMe24\\temp_project\\src\\hooks\\useAuth.ts",
            "fileType": ".ts",
            "linesAdded": 140,
            "linesRemoved": 0,
            "projectName": "FixMe24",
            "content": {
              "added": [],
              "removed": []
            },
            "duration": 1,
            "language": "ts"
          },
          {
            "timestamp": "2025-05-21T03:56:49.470Z",
            "fileName": "c:\\Users\\pk-20\\Projekte\\FixMe24\\temp_project\\src\\hooks\\useAuth.ts",
            "fileType": ".ts",
            "linesAdded": 0,
            "linesRemoved": 1,
            "projectName": "FixMe24",
            "content": {
              "added": [],
              "removed": []
            },
            "duration": 1,
            "language": "ts"
          }
        ],
        "c:\\Users\\pk-20\\Projekte\\FixMe24\\temp_project\\src\\i18n\\index.ts": [
          {
            "timestamp": "2025-05-21T03:57:02.287Z",
            "fileName": "c:\\Users\\pk-20\\Projekte\\FixMe24\\temp_project\\src\\i18n\\index.ts",
            "fileType": ".ts",
            "linesAdded": 34,
            "linesRemoved": 0,
            "projectName": "FixMe24",
            "content": {
              "added": [],
              "removed": []
            },
            "duration": 1,
            "language": "ts"
          },
          {
            "timestamp": "2025-05-21T03:57:02.589Z",
            "fileName": "c:\\Users\\pk-20\\Projekte\\FixMe24\\temp_project\\src\\i18n\\index.ts",
            "fileType": ".ts",
            "linesAdded": 0,
            "linesRemoved": 1,
            "projectName": "FixMe24",
            "content": {
              "added": [],
              "removed": []
            },
            "duration": 1,
            "language": "ts"
          }
        ],
        "c:\\Users\\pk-20\\Projekte\\FixMe24\\temp_project\\src\\i18n\\locales\\en.ts": [
          {
            "timestamp": "2025-05-21T03:57:31.837Z",
            "fileName": "c:\\Users\\pk-20\\Projekte\\FixMe24\\temp_project\\src\\i18n\\locales\\en.ts",
            "fileType": ".ts",
            "linesAdded": 1,
            "linesRemoved": 0,
            "projectName": "FixMe24",
            "content": {
              "added": [],
              "removed": []
            },
            "duration": 1,
            "language": "ts"
          },
          {
            "timestamp": "2025-05-21T03:57:33.839Z",
            "fileName": "c:\\Users\\pk-20\\Projekte\\FixMe24\\temp_project\\src\\i18n\\locales\\en.ts",
            "fileType": ".ts",
            "linesAdded": 135,
            "linesRemoved": 0,
            "projectName": "FixMe24",
            "content": {
              "added": [],
              "removed": []
            },
            "duration": 1,
            "language": "ts"
          },
          {
            "timestamp": "2025-05-21T03:57:37.096Z",
            "fileName": "c:\\Users\\pk-20\\Projekte\\FixMe24\\temp_project\\src\\i18n\\locales\\en.ts",
            "fileType": ".ts",
            "linesAdded": 0,
            "linesRemoved": 1,
            "projectName": "FixMe24",
            "content": {
              "added": [],
              "removed": []
            },
            "duration": 1,
            "language": "ts"
          }
        ],
        "c:\\Users\\pk-20\\Projekte\\FixMe24\\temp_project\\src\\i18n\\locales\\de.ts": [
          {
            "timestamp": "2025-05-21T03:58:09.993Z",
            "fileName": "c:\\Users\\pk-20\\Projekte\\FixMe24\\temp_project\\src\\i18n\\locales\\de.ts",
            "fileType": ".ts",
            "linesAdded": 1,
            "linesRemoved": 0,
            "projectName": "FixMe24",
            "content": {
              "added": [],
              "removed": []
            },
            "duration": 1,
            "language": "ts"
          },
          {
            "timestamp": "2025-05-21T03:58:11.552Z",
            "fileName": "c:\\Users\\pk-20\\Projekte\\FixMe24\\temp_project\\src\\i18n\\locales\\de.ts",
            "fileType": ".ts",
            "linesAdded": 135,
            "linesRemoved": 0,
            "projectName": "FixMe24",
            "content": {
              "added": [],
              "removed": []
            },
            "duration": 1,
            "language": "ts"
          },
          {
            "timestamp": "2025-05-21T03:58:14.859Z",
            "fileName": "c:\\Users\\pk-20\\Projekte\\FixMe24\\temp_project\\src\\i18n\\locales\\de.ts",
            "fileType": ".ts",
            "linesAdded": 0,
            "linesRemoved": 1,
            "projectName": "FixMe24",
            "content": {
              "added": [],
              "removed": []
            },
            "duration": 1,
            "language": "ts"
          }
        ],
        "c:\\Users\\pk-20\\Projekte\\FixMe24\\temp_project\\src\\app\\layout.tsx": [
          {
            "timestamp": "2025-05-21T03:58:33.681Z",
            "fileName": "c:\\Users\\pk-20\\Projekte\\FixMe24\\temp_project\\src\\app\\layout.tsx",
            "fileType": ".tsx",
            "linesAdded": 35,
            "linesRemoved": 0,
            "projectName": "FixMe24",
            "content": {
              "added": [],
              "removed": []
            },
            "duration": 1,
            "language": "tsx"
          },
          {
            "timestamp": "2025-05-21T03:58:35.829Z",
            "fileName": "c:\\Users\\pk-20\\Projekte\\FixMe24\\temp_project\\src\\app\\layout.tsx",
            "fileType": ".tsx",
            "linesAdded": 16,
            "linesRemoved": 0,
            "projectName": "FixMe24",
            "content": {
              "added": [],
              "removed": []
            },
            "duration": 1,
            "language": "tsx"
          },
          {
            "timestamp": "2025-05-21T04:02:13.930Z",
            "fileName": "c:\\Users\\pk-20\\Projekte\\FixMe24\\temp_project\\src\\app\\layout.tsx",
            "fileType": ".tsx",
            "linesAdded": 3,
            "linesRemoved": 0,
            "projectName": "FixMe24",
            "content": {
              "added": [],
              "removed": []
            },
            "duration": 1,
            "language": "tsx"
          }
        ],
        "c:\\Users\\pk-20\\Projekte\\FixMe24\\temp_project\\src\\app\\page.tsx": [
          {
            "timestamp": "2025-05-21T04:00:18.272Z",
            "fileName": "c:\\Users\\pk-20\\Projekte\\FixMe24\\temp_project\\src\\app\\page.tsx",
            "fileType": ".tsx",
            "linesAdded": 203,
            "linesRemoved": 0,
            "projectName": "FixMe24",
            "content": {
              "added": [],
              "removed": []
            },
            "duration": 2,
            "language": "tsx"
          }
        ],
        "c:\\Users\\pk-20\\Projekte\\FixMe24\\temp_project\\public\\images\\hero-illustration.svg": [
          {
            "timestamp": "2025-05-21T04:00:54.420Z",
            "fileName": "c:\\Users\\pk-20\\Projekte\\FixMe24\\temp_project\\public\\images\\hero-illustration.svg",
            "fileType": ".svg",
            "linesAdded": 34,
            "linesRemoved": 0,
            "projectName": "FixMe24",
            "content": {
              "added": [],
              "removed": []
            },
            "duration": 1,
            "language": "svg"
          }
        ],
        "c:\\Users\\pk-20\\Projekte\\FixMe24\\temp_project\\src\\utils\\content.ts": [
          {
            "timestamp": "2025-05-21T04:01:20.847Z",
            "fileName": "c:\\Users\\pk-20\\Projekte\\FixMe24\\temp_project\\src\\utils\\content.ts",
            "fileType": ".ts",
            "linesAdded": 118,
            "linesRemoved": 0,
            "projectName": "FixMe24",
            "content": {
              "added": [],
              "removed": []
            },
            "duration": 1,
            "language": "ts"
          },
          {
            "timestamp": "2025-05-21T04:01:26.767Z",
            "fileName": "c:\\Users\\pk-20\\Projekte\\FixMe24\\temp_project\\src\\utils\\content.ts",
            "fileType": ".ts",
            "linesAdded": 0,
            "linesRemoved": 1,
            "projectName": "FixMe24",
            "content": {
              "added": [],
              "removed": []
            },
            "duration": 1,
            "language": "ts"
          }
        ],
        "c:\\Users\\pk-20\\Projekte\\FixMe24\\temp_project\\src\\providers\\QueryProvider.tsx": [
          {
            "timestamp": "2025-05-21T04:01:39.156Z",
            "fileName": "c:\\Users\\pk-20\\Projekte\\FixMe24\\temp_project\\src\\providers\\QueryProvider.tsx",
            "fileType": ".tsx",
            "linesAdded": 1,
            "linesRemoved": 0,
            "projectName": "FixMe24",
            "content": {
              "added": [],
              "removed": []
            },
            "duration": 1,
            "language": "tsx"
          },
          {
            "timestamp": "2025-05-21T04:01:39.132Z",
            "fileName": "c:\\Users\\pk-20\\Projekte\\FixMe24\\temp_project\\src\\providers\\QueryProvider.tsx",
            "fileType": ".tsx",
            "linesAdded": 27,
            "linesRemoved": 0,
            "projectName": "FixMe24",
            "content": {
              "added": [],
              "removed": []
            },
            "duration": 1,
            "language": "tsx"
          },
          {
            "timestamp": "2025-05-21T04:01:44.222Z",
            "fileName": "c:\\Users\\pk-20\\Projekte\\FixMe24\\temp_project\\src\\providers\\QueryProvider.tsx",
            "fileType": ".tsx",
            "linesAdded": 0,
            "linesRemoved": 1,
            "projectName": "FixMe24",
            "content": {
              "added": [],
              "removed": []
            },
            "duration": 1,
            "language": "tsx"
          }
        ],
        "c:\\Users\\pk-20\\Projekte\\FixMe24\\temp_project\\src\\app\\auth\\login\\page.tsx": [
          {
            "timestamp": "2025-05-21T04:02:45.272Z",
            "fileName": "c:\\Users\\pk-20\\Projekte\\FixMe24\\temp_project\\src\\app\\auth\\login\\page.tsx",
            "fileType": ".tsx",
            "linesAdded": 1,
            "linesRemoved": 0,
            "projectName": "FixMe24",
            "content": {
              "added": [],
              "removed": []
            },
            "duration": 1,
            "language": "tsx"
          },
          {
            "timestamp": "2025-05-21T04:02:46.527Z",
            "fileName": "c:\\Users\\pk-20\\Projekte\\FixMe24\\temp_project\\src\\app\\auth\\login\\page.tsx",
            "fileType": ".tsx",
            "linesAdded": 154,
            "linesRemoved": 0,
            "projectName": "FixMe24",
            "content": {
              "added": [],
              "removed": []
            },
            "duration": 1,
            "language": "tsx"
          },
          {
            "timestamp": "2025-05-21T04:02:47.939Z",
            "fileName": "c:\\Users\\pk-20\\Projekte\\FixMe24\\temp_project\\src\\app\\auth\\login\\page.tsx",
            "fileType": ".tsx",
            "linesAdded": 0,
            "linesRemoved": 1,
            "projectName": "FixMe24",
            "content": {
              "added": [],
              "removed": []
            },
            "duration": 1,
            "language": "tsx"
          }
        ],
        "c:\\Users\\pk-20\\Projekte\\FixMe24\\temp_project\\src\\app\\auth\\register\\page.tsx": [
          {
            "timestamp": "2025-05-21T04:03:53.366Z",
            "fileName": "c:\\Users\\pk-20\\Projekte\\FixMe24\\temp_project\\src\\app\\auth\\register\\page.tsx",
            "fileType": ".tsx",
            "linesAdded": 268,
            "linesRemoved": 0,
            "projectName": "FixMe24",
            "content": {
              "added": [],
              "removed": []
            },
            "duration": 2,
            "language": "tsx"
          },
          {
            "timestamp": "2025-05-21T04:03:58.330Z",
            "fileName": "c:\\Users\\pk-20\\Projekte\\FixMe24\\temp_project\\src\\app\\auth\\register\\page.tsx",
            "fileType": ".tsx",
            "linesAdded": 0,
            "linesRemoved": 1,
            "projectName": "FixMe24",
            "content": {
              "added": [],
              "removed": []
            },
            "duration": 1,
            "language": "tsx"
          }
        ],
        "c:\\Users\\pk-20\\Projekte\\FixMe24\\temp_project\\src\\app\\services\\page.tsx": [
          {
            "timestamp": "2025-05-21T04:07:41.530Z",
            "fileName": "c:\\Users\\pk-20\\Projekte\\FixMe24\\temp_project\\src\\app\\services\\page.tsx",
            "fileType": ".tsx",
            "linesAdded": 170,
            "linesRemoved": 0,
            "projectName": "FixMe24",
            "content": {
              "added": [],
              "removed": []
            },
            "duration": 4,
            "language": "tsx"
          }
        ],
        "c:\\Users\\pk-20\\Projekte\\FixMe24\\temp_project\\src\\app\\projects\\page.tsx": [
          {
            "timestamp": "2025-05-21T04:08:29.920Z",
            "fileName": "c:\\Users\\pk-20\\Projekte\\FixMe24\\temp_project\\src\\app\\projects\\page.tsx",
            "fileType": ".tsx",
            "linesAdded": 175,
            "linesRemoved": 0,
            "projectName": "FixMe24",
            "content": {
              "added": [],
              "removed": []
            },
            "duration": 1,
            "language": "tsx"
          }
        ],
        "c:\\Users\\pk-20\\Projekte\\FixMe24\\temp_project\\src\\app\\news\\page.tsx": [
          {
            "timestamp": "2025-05-21T04:09:16.920Z",
            "fileName": "c:\\Users\\pk-20\\Projekte\\FixMe24\\temp_project\\src\\app\\news\\page.tsx",
            "fileType": ".tsx",
            "linesAdded": 1,
            "linesRemoved": 0,
            "projectName": "FixMe24",
            "content": {
              "added": [],
              "removed": []
            },
            "duration": 1,
            "language": "tsx"
          },
          {
            "timestamp": "2025-05-21T04:09:22.231Z",
            "fileName": "c:\\Users\\pk-20\\Projekte\\FixMe24\\temp_project\\src\\app\\news\\page.tsx",
            "fileType": ".tsx",
            "linesAdded": 197,
            "linesRemoved": 0,
            "projectName": "FixMe24",
            "content": {
              "added": [],
              "removed": []
            },
            "duration": 1,
            "language": "tsx"
          },
          {
            "timestamp": "2025-05-21T04:09:27.029Z",
            "fileName": "c:\\Users\\pk-20\\Projekte\\FixMe24\\temp_project\\src\\app\\news\\page.tsx",
            "fileType": ".tsx",
            "linesAdded": 0,
            "linesRemoved": 1,
            "projectName": "FixMe24",
            "content": {
              "added": [],
              "removed": []
            },
            "duration": 1,
            "language": "tsx"
          }
        ],
        "c:\\Users\\pk-20\\Projekte\\FixMe24\\temp_project\\src\\app\\contact\\page.tsx": [
          {
            "timestamp": "2025-05-21T04:10:26.854Z",
            "fileName": "c:\\Users\\pk-20\\Projekte\\FixMe24\\temp_project\\src\\app\\contact\\page.tsx",
            "fileType": ".tsx",
            "linesAdded": 1,
            "linesRemoved": 0,
            "projectName": "FixMe24",
            "content": {
              "added": [],
              "removed": []
            },
            "duration": 1,
            "language": "tsx"
          },
          {
            "timestamp": "2025-05-21T04:10:29.342Z",
            "fileName": "c:\\Users\\pk-20\\Projekte\\FixMe24\\temp_project\\src\\app\\contact\\page.tsx",
            "fileType": ".tsx",
            "linesAdded": 282,
            "linesRemoved": 0,
            "projectName": "FixMe24",
            "content": {
              "added": [],
              "removed": []
            },
            "duration": 1,
            "language": "tsx"
          },
          {
            "timestamp": "2025-05-21T04:10:32.931Z",
            "fileName": "c:\\Users\\pk-20\\Projekte\\FixMe24\\temp_project\\src\\app\\contact\\page.tsx",
            "fileType": ".tsx",
            "linesAdded": 0,
            "linesRemoved": 1,
            "projectName": "FixMe24",
            "content": {
              "added": [],
              "removed": []
            },
            "duration": 1,
            "language": "tsx"
          }
        ],
        "c:\\Users\\pk-20\\Projekte\\FixMe24\\temp_project\\src\\app\\admin\\dashboard\\page.tsx": [
          {
            "timestamp": "2025-05-21T04:11:33.255Z",
            "fileName": "c:\\Users\\pk-20\\Projekte\\FixMe24\\temp_project\\src\\app\\admin\\dashboard\\page.tsx",
            "fileType": ".tsx",
            "linesAdded": 1,
            "linesRemoved": 0,
            "projectName": "FixMe24",
            "content": {
              "added": [],
              "removed": []
            },
            "duration": 2,
            "language": "tsx"
          },
          {
            "timestamp": "2025-05-21T04:11:35.858Z",
            "fileName": "c:\\Users\\pk-20\\Projekte\\FixMe24\\temp_project\\src\\app\\admin\\dashboard\\page.tsx",
            "fileType": ".tsx",
            "linesAdded": 275,
            "linesRemoved": 0,
            "projectName": "FixMe24",
            "content": {
              "added": [],
              "removed": []
            },
            "duration": 1,
            "language": "tsx"
          },
          {
            "timestamp": "2025-05-21T04:11:39.478Z",
            "fileName": "c:\\Users\\pk-20\\Projekte\\FixMe24\\temp_project\\src\\app\\admin\\dashboard\\page.tsx",
            "fileType": ".tsx",
            "linesAdded": 0,
            "linesRemoved": 1,
            "projectName": "FixMe24",
            "content": {
              "added": [],
              "removed": []
            },
            "duration": 1,
            "language": "tsx"
          }
        ],
        "c:\\Users\\pk-20\\Projekte\\FixMe24\\temp_project\\src\\app\\admin\\layout.tsx": [
          {
            "timestamp": "2025-05-21T04:12:15.951Z",
            "fileName": "c:\\Users\\pk-20\\Projekte\\FixMe24\\temp_project\\src\\app\\admin\\layout.tsx",
            "fileType": ".tsx",
            "linesAdded": 1,
            "linesRemoved": 0,
            "projectName": "FixMe24",
            "content": {
              "added": [],
              "removed": []
            },
            "duration": 1,
            "language": "tsx"
          },
          {
            "timestamp": "2025-05-21T04:12:17.113Z",
            "fileName": "c:\\Users\\pk-20\\Projekte\\FixMe24\\temp_project\\src\\app\\admin\\layout.tsx",
            "fileType": ".tsx",
            "linesAdded": 174,
            "linesRemoved": 0,
            "projectName": "FixMe24",
            "content": {
              "added": [],
              "removed": []
            },
            "duration": 1,
            "language": "tsx"
          },
          {
            "timestamp": "2025-05-21T04:12:21.135Z",
            "fileName": "c:\\Users\\pk-20\\Projekte\\FixMe24\\temp_project\\src\\app\\admin\\layout.tsx",
            "fileType": ".tsx",
            "linesAdded": 0,
            "linesRemoved": 1,
            "projectName": "FixMe24",
            "content": {
              "added": [],
              "removed": []
            },
            "duration": 1,
            "language": "tsx"
          }
        ],
        "c:\\Users\\pk-20\\Projekte\\FixMe24\\temp_project\\public\\robots.txt": [
          {
            "timestamp": "2025-05-21T04:12:38.804Z",
            "fileName": "c:\\Users\\pk-20\\Projekte\\FixMe24\\temp_project\\public\\robots.txt",
            "fileType": ".txt",
            "linesAdded": 1,
            "linesRemoved": 0,
            "projectName": "FixMe24",
            "content": {
              "added": [],
              "removed": []
            },
            "duration": 1,
            "language": "txt"
          },
          {
            "timestamp": "2025-05-21T04:12:40.176Z",
            "fileName": "c:\\Users\\pk-20\\Projekte\\FixMe24\\temp_project\\public\\robots.txt",
            "fileType": ".txt",
            "linesAdded": 8,
            "linesRemoved": 0,
            "projectName": "FixMe24",
            "content": {
              "added": [],
              "removed": []
            },
            "duration": 1,
            "language": "txt"
          }
        ],
        "c:\\Users\\pk-20\\Projekte\\FixMe24\\temp_project\\public\\sitemap.xml": [
          {
            "timestamp": "2025-05-21T04:12:57.660Z",
            "fileName": "c:\\Users\\pk-20\\Projekte\\FixMe24\\temp_project\\public\\sitemap.xml",
            "fileType": ".xml",
            "linesAdded": 1,
            "linesRemoved": 0,
            "projectName": "FixMe24",
            "content": {
              "added": [],
              "removed": []
            },
            "duration": 1,
            "language": "xml"
          },
          {
            "timestamp": "2025-05-21T04:12:58.390Z",
            "fileName": "c:\\Users\\pk-20\\Projekte\\FixMe24\\temp_project\\public\\sitemap.xml",
            "fileType": ".xml",
            "linesAdded": 52,
            "linesRemoved": 0,
            "projectName": "FixMe24",
            "content": {
              "added": [],
              "removed": []
            },
            "duration": 1,
            "language": "xml"
          }
        ],
        "c:\\Users\\pk-20\\Projekte\\FixMe24\\temp_project\\src\\components\\common\\SEO.tsx": [
          {
            "timestamp": "2025-05-21T04:13:23.773Z",
            "fileName": "c:\\Users\\pk-20\\Projekte\\FixMe24\\temp_project\\src\\components\\common\\SEO.tsx",
            "fileType": ".tsx",
            "linesAdded": 1,
            "linesRemoved": 0,
            "projectName": "FixMe24",
            "content": {
              "added": [],
              "removed": []
            },
            "duration": 1,
            "language": "tsx"
          },
          {
            "timestamp": "2025-05-21T04:13:25.580Z",
            "fileName": "c:\\Users\\pk-20\\Projekte\\FixMe24\\temp_project\\src\\components\\common\\SEO.tsx",
            "fileType": ".tsx",
            "linesAdded": 85,
            "linesRemoved": 0,
            "projectName": "FixMe24",
            "content": {
              "added": [],
              "removed": []
            },
            "duration": 1,
            "language": "tsx"
          },
          {
            "timestamp": "2025-05-21T04:13:29.772Z",
            "fileName": "c:\\Users\\pk-20\\Projekte\\FixMe24\\temp_project\\src\\components\\common\\SEO.tsx",
            "fileType": ".tsx",
            "linesAdded": 0,
            "linesRemoved": 1,
            "projectName": "FixMe24",
            "content": {
              "added": [],
              "removed": []
            },
            "duration": 1,
            "language": "tsx"
          }
        ],
        "c:\\Users\\pk-20\\Projekte\\FixMe24\\temp_project\\src\\app\\services\\[id]\\page.tsx": [
          {
            "timestamp": "2025-05-21T04:14:10.785Z",
            "fileName": "c:\\Users\\pk-20\\Projekte\\FixMe24\\temp_project\\src\\app\\services\\[id]\\page.tsx",
            "fileType": ".tsx",
            "linesAdded": 207,
            "linesRemoved": 0,
            "projectName": "FixMe24",
            "content": {
              "added": [],
              "removed": []
            },
            "duration": 1,
            "language": "tsx"
          },
          {
            "timestamp": "2025-05-21T04:14:15.618Z",
            "fileName": "c:\\Users\\pk-20\\Projekte\\FixMe24\\temp_project\\src\\app\\services\\[id]\\page.tsx",
            "fileType": ".tsx",
            "linesAdded": 0,
            "linesRemoved": 1,
            "projectName": "FixMe24",
            "content": {
              "added": [],
              "removed": []
            },
            "duration": 1,
            "language": "tsx"
          }
        ]
      },
      "languageStats": {
        "tsx": 9,
        "ts": 8
      },
      "changeFrequency": {
        "5": 17
      },
      "topFiles": [
        "c:\\Users\\pk-20\\Projekte\\FixMe24\\temp_project\\src\\components\\layout\\Header.tsx",
        "c:\\Users\\pk-20\\Projekte\\FixMe24\\temp_project\\src\\components\\layout\\Footer.tsx",
        "c:\\Users\\pk-20\\Projekte\\FixMe24\\temp_project\\src\\hooks\\useAuth.ts",
        "c:\\Users\\pk-20\\Projekte\\FixMe24\\temp_project\\src\\i18n\\locales\\en.ts",
        "c:\\Users\\pk-20\\Projekte\\FixMe24\\temp_project\\src\\components\\layout\\MainLayout.tsx"
      ],
      "averageChangeSize": 40.666666666666664
    }
  },
  "totalActiveTime": 16,
  "totalProjects": 1,
  "totalFiles": 7,
  "mostActiveHours": [
    5
  ],
  "mostUsedLanguages": [
    "tsx",
    "ts"
  ]
}